setup.py
on_http_redfish_1_0/__init__.py
on_http_redfish_1_0/api_client.py
on_http_redfish_1_0/configuration.py
on_http_redfish_1_0/rest.py
on_http_redfish_1_0.egg-info/PKG-INFO
on_http_redfish_1_0.egg-info/SOURCES.txt
on_http_redfish_1_0.egg-info/dependency_links.txt
on_http_redfish_1_0.egg-info/requires.txt
on_http_redfish_1_0.egg-info/top_level.txt
on_http_redfish_1_0/apis/__init__.py
on_http_redfish_1_0/apis/redfishv_api.py
on_http_redfish_1_0/models/__init__.py
on_http_redfish_1_0/models/account_service_1_0_0_account_service.py
on_http_redfish_1_0/models/bios_change_password.py
on_http_redfish_1_0/models/bios_reset_bios.py
on_http_redfish_1_0/models/bios_v1_0_0_actions.py
on_http_redfish_1_0/models/bios_v1_0_0_attributes.py
on_http_redfish_1_0/models/bios_v1_0_0_oem_actions.py
on_http_redfish_1_0/models/bios_v1_0_1_bios.py
on_http_redfish_1_0/models/chassis_1_0_0_chassis.py
on_http_redfish_1_0/models/chassis_1_0_0_chassis_actions.py
on_http_redfish_1_0/models/chassis_1_0_0_chassis_links.py
on_http_redfish_1_0/models/chassis_1_0_0_reset.py
on_http_redfish_1_0/models/chassis_collection_chassis_collection.py
on_http_redfish_1_0/models/computer_system_1_0_0_boot.py
on_http_redfish_1_0/models/computer_system_1_0_0_computer_system.py
on_http_redfish_1_0/models/computer_system_1_0_0_computer_system_actions.py
on_http_redfish_1_0/models/computer_system_1_0_0_computer_system_links.py
on_http_redfish_1_0/models/computer_system_1_0_0_memory_summary.py
on_http_redfish_1_0/models/computer_system_1_0_0_processor_summary.py
on_http_redfish_1_0/models/computer_system_1_0_0_reset.py
on_http_redfish_1_0/models/computer_system_collection_computer_system_collection.py
on_http_redfish_1_0/models/dcim_cooling_collection_dcim_cooling_collection.py
on_http_redfish_1_0/models/drive_add_hotspare.py
on_http_redfish_1_0/models/endpoint_endpoint.py
on_http_redfish_1_0/models/error_response.py
on_http_redfish_1_0/models/ethernet_interface_collection_ethernet_interface_collection.py
on_http_redfish_1_0/models/ethernet_interface_ethernet_interface.py
on_http_redfish_1_0/models/ethernet_interface_v1_0_0_i_pv6_address_policy_entry.py
on_http_redfish_1_0/models/ethernet_interface_v1_0_0_mac_address.py
