Metadata-Version: 1.0
Name: on-http-redfish-1-0
Version: 1.0.9
Summary: rackhd redfish v1
Home-page: UNKNOWN
Author: UNKNOWN
Author-email: UNKNOWN
License: UNKNOWN
Keywords: Swagger,rackhd redfish v1
Platform: UNKNOWN
